azure_interactive_shortcuts/__init__.py
azure_interactive_shortcuts/__main__.py
azure_interactive_shortcuts/_public_vm_ip.py
azure_interactive_shortcuts-0.1.0.dist-info/entry_points.txt
azure_interactive_shortcuts-0.1.0.dist-info/WHEEL
azure_interactive_shortcuts-0.1.0.dist-info/METADATA
azure_interactive_shortcuts-0.1.0.dist-info/RECORD
