Metadata-Version: 2.1
Name: azure-interactive-shortcuts
Version: 0.1.0
Summary: Helpful tools for using Azure resources interactively at the command line
Home-page: https://github.com/aatifsyed/azure-interactive-shortcuts
License: MIT
Author: Aatif Syed
Author-email: aatifsyedyp@gmail.com
Requires-Python: >=3.8,<4.0
Classifier: License :: OSI Approved :: MIT License
Classifier: Programming Language :: Python :: 3
Classifier: Programming Language :: Python :: 3.10
Classifier: Programming Language :: Python :: 3.8
Classifier: Programming Language :: Python :: 3.9
Requires-Dist: argcomplete (>=2.0.0,<3.0.0)
Requires-Dist: dataclasses-json (>=0.5.6,<0.6.0)
Requires-Dist: logging-actions (>=0.1.6,<0.2.0)
Requires-Dist: prompt-toolkit (>=3.0.24,<4.0.0)
Requires-Dist: returns (>=0.18.0,<0.19.0)
Requires-Dist: rich (>=11.0.0,<12.0.0)
Project-URL: Repository, https://github.com/aatifsyed/azure-interactive-shortcuts
